{
    "id": "1",
    "title": "Insomnia",
    "thumbnail": "/content/image/insomnia.png",
    "description": "내가 민성이를 구할 수 있을까?",
    "recommendations": 245,
    "content": "![INSOMNIA 썸네일](/content/image/insomniaSecond.jpg)\n\n## Insomnia\n\n**내가 민성이를 구할 수 있을까?**\n\n---\n\n**울고 있던 꼬마아이를 돕기로 결심이 서자, 마음이 편해졌다.**  \n하지만 그것도 잠시, 정신을 잃었다가 눈을 뜨니 나는 끝이 어딘지 모를 어둠 속에서 처음 보는 4명의 사람들과 깨어났다.  \n그리고 그들도 나를 처음 보는 듯 했다.\n\n대체 이 곳은 어디일까. 그리고 저들은 누구일까.\n\n나는 나를 숨겨야 할까. 아니면, 어디까지 나의 비밀을 알려줘도 되는 걸까.  \n나는 그 꼬마아이를 구할 수 있을까.\n\n---\n\n## 🔒 INSOMNIA의 규칙\n\n1. 서로 예의를 갖춰 대화해주세요. 모니터 너머엔 사람이 있습니다.  \n2. 욕설은 금지! 바른 말, 고운 말을 사용하며 대화해보아요.  \n3. 몰입을 깨지 않는 선에서 모든 행동과 모든 말이 가능합니다.  \n4. ???  \n5. ???  \n6. ???  \n7. ???  \n8. ???  \n9. ???  \n10. ???  \n",
    "tags": ["추리", "합작"],
    "password": "인섬니아",
    "makers": ["수암수암", "변상훈", "버니허터칩"],
    "players": 5,
    "characters": ["???", "????", "??", "????", "??"],
    "price": 5000,
    "time": 150,
    "contact": "https://open.kakao.com/o/s76Y10ke",
    "createdBy": "system",
    "updatedBy": "system",
    "createdAt": "2025-04-13T00:00:00.000Z",
    "updatedAt": "2025-04-13T00:00:00.000Z"
}
