{
    "id": "8",
    "name": "κ¶ν•μ—…κΈ€",
    "description": "ν¬μΈνΈλ¥Ό μ‚¬μ©ν•΄ μ›ν•λ” κΈ°λ¥μ λ΄‡ κ¶ν•μ„ μ—…κ·Έλ μ΄λ“ν•  μ μλ” λ…λ Ήμ–΄μ…λ‹λ‹¤.",
    "usage": "/κ¶ν•μ—…κΈ€ λ΄‡κ¶ν•:[κ¶ν• μ΄λ¦„]",
    "category": "μ μ €",
    "requiredPermissions": ["κ³µν†µ"],
    "content": "### π… **κ¶ν•μ—…κΈ€ λ…λ Ήμ–΄: ν¬μΈνΈ μ‚¬μ©μΌλ΅ κ¶ν• μ—…κ·Έλ μ΄λ“**\n\n**\"λƒ¥λƒ¥~! μ›ν•λ” κΈ°λ¥μ„ μ‚¬μ©ν•λ ¤λ©΄ ν¬μΈνΈλ΅ κ¶ν•μ„ μ—…κ·Έλ μ΄λ“ν•μ„Έμ”!\"**\n\n---\n\n## π› οΈ **κ¶ν•μ—…κΈ€ λ…λ Ήμ–΄ μ‚¬μ©λ²•**\n\nμ΄ λ…λ Ήμ–΄λ” **ν¬μΈνΈλ¥Ό μ‚¬μ©ν•μ—¬ μ¶”κ°€μ μΈ λ΄‡ κ¶ν•μ„ νλ“**ν•λ” κΈ°λ¥μ„ μ κ³µν•©λ‹λ‹¤.  \nκ¶ν•μ„ μ—…κ·Έλ μ΄λ“ν•λ©΄ **λ΄‡μ νΉμ • κΈ°λ¥μ„ μ‚¬μ©ν•  μ μλ„λ΅ ν•΄μ **ν•  μ μμµλ‹λ‹¤.\n\n### **λ…λ Ήμ–΄ ν•μ‹:**\n\n- **κ¶ν• λ©λ΅ ν™•μΈ:**\n  ```\n  /κ¶ν•μ—…κΈ€\n  !κ¶ν•μ—…κΈ€\n  ```\n\n- **νΉμ • κ¶ν• κµ¬λ§¤:**\n  ```\n  /κ¶ν•μ—…κΈ€ λ΄‡κ¶ν•:[μ›ν•λ” κ¶ν• μ΄λ¦„]\n  !κ¶ν•μ—…κΈ€ [μ›ν•λ” κ¶ν• μ΄λ¦„]\n  ```\n\nπ“ **κ¶ν• λ©λ΅μ„ ν™•μΈν• ν›„, μ›ν•λ” κ¶ν•μ„ κµ¬λ§¤ν•μ„Έμ”!**\nπ“ **ν„μ¬ κ¶ν• μ‹μ¤ν…μ€ μ„μ‹μ μΌλ΅ μ΄μλλ©°, μ¶”ν›„ μ—…λ°μ΄νΈλ  μ μμµλ‹λ‹¤.**\n\n---\n\n## ποΈ **ν¬μΈνΈ λ° κ¶ν• μ‹μ¤ν… κ°μ”**\n\n### **ν¬μΈνΈ νλ“ λ°©λ²•**\n\nν¬μΈνΈλ” **12μλ¦¬ μ½”λ“**λ¥Ό μ…λ ¥ν•μ—¬ νλ“ν•  μ μμµλ‹λ‹¤.\n\nβ… μ½”λ“ μ…λ ¥ μμ‹:\n```\n/μ½”λ“ μ½”λ“:ABC123XYZ789\n```\n\nβ… μ¶λ ¥:\n```\nβ… 5000 ν¬μΈνΈκ°€ μ§€κΈ‰λμ—μµλ‹λ‹¤!\nν„μ¬ λ³΄μ  ν¬μΈνΈ: 12,500\n```\n\nπ“ **κ° μ½”λ“λ” 1νλ§ μ‚¬μ© κ°€λ¥ν•λ©°, μ¤‘λ³µ μ…λ ¥μ€ λ¶κ°€λ¥ν•©λ‹λ‹¤.**\nπ“ **νλ“ν• ν¬μΈνΈλ” `/κ¶ν•μ—…κΈ€` λ…λ Ήμ–΄λ¥Ό ν†µν•΄ μ‚¬μ©ν•  μ μμµλ‹λ‹¤.**\n\n---\n\n## π› οΈ **κ¶ν• λ©λ΅ λ° κ°€κ²©**\n\n| π… κ¶ν• μ΄λ¦„                                            | π’° κ°€κ²© (ν¬μΈνΈ) | π”Ή μ„¤λ…                                                  |\n|----------------------------------------------------------|------------------|-----------------------------------------------------------|\n| **λ¬΄μ ν• μ νλΈ λ§ν¬ μ¶”κ°€** (`URL_UNLIMIT`)             | 1000 ν¬μΈνΈ      | μ νλΈ μ£Όμ† μ¶”κ°€ κ°μ μ ν• ν•΄μ                           |\n| **κ΄€μ „ λ…λ Ή μ‚¬μ©** (`OBSERVER`)                         | 1000 ν¬μΈνΈ      | `/κ΄€μ „` λ…λ Ήμ–΄ μ‚¬μ© κ°€λ¥                                 |\n| **κ³ μμ§ μμ•… ν”λ μ΄** (`AUDIO_BIT_RATE`)               | 1500 ν¬μΈνΈ      | λ” λ†’μ€ λΉ„νΈλ μ΄νΈ(μμ§)λ΅ μμ•… μ¬μƒ κ°€λ¥                |\n| **μλ™ μ²­μ† κΈ°λ¥** (`AUTO_CLEAN`)                       | 1000 ν¬μΈνΈ      | μλ™μΌλ΅ νΉμ • λ©”μ‹μ§€λ¥Ό μ‚­μ ν•λ” κΈ°λ¥ (λ―Έκµ¬ν„)            |\n| **κΈΈλ“ μ¶”κ°€** (`ADD_GUILD_ABLE`)                        | -                | νΉμ • μ μ €λ§ λ¶€μ—¬λ°›μ„ μ μλ” νΉλ³„ κ¶ν•                   |\n| **μμ•… νμΌ μ €μ¥ λ° ν”λ μ΄ (100MB)** (`LOCAL_MUSIC`)    | 2000 ν¬μΈνΈ      | λ΅μ»¬ μμ•… νμΌ μ €μ¥ λ° μ¬μƒ κ°€λ¥ (μµλ€ 100MB)            |\n| **μμ•… νμΌ μ €μ¥ λ° ν”λ μ΄ (200MB)** (`LOCAL_MUSIC_UP`) | 2000 ν¬μΈνΈ      | λ΅μ»¬ μμ•… μ €μ¥ κ³µκ°„μ„ 200MBλ΅ ν™•μ¥ (**μ„ ν–‰ κ¶ν• ν•„μ”!**) |\n\nπ“ **μΌλ¶€ κ¶ν•μ€ μ„ ν–‰ κ¶ν•μ΄ μμ–΄μ•Όλ§ κµ¬λ§¤κ°€ κ°€λ¥ν•©λ‹λ‹¤.**\nπ“ **κ¶ν• μ‹μ¤ν…μ€ ν–¥ν›„ μ—…λ°μ΄νΈλ¥Ό ν†µν•΄ ν™•μ¥λ  μμ •μ…λ‹λ‹¤.**\n\n---\n\n## β… **μ„±κ³µμ μΈ κ¶ν• μ—…κ·Έλ μ΄λ“ μμ‹**\n\n### μ…λ ¥:\n```\n/κ¶ν•μ—…κΈ€ λ΄‡κ¶ν•:LOCAL_MUSIC\n```\n\n### μ¶λ ¥:\n```\nβ… μμ•…νμΌ μ €μ¥ λ° ν”λ μ΄ (100MB) κ¶ν•μ΄ μ„±κ³µμ μΌλ΅ λ¶€μ—¬λμ—μµλ‹λ‹¤.\n```\n\n---\n\n## β **μ¤λ¥ λ©”μ‹μ§€ μμ‹**\n\n1οΈβƒ£ **ν¬μΈνΈ λ¶€μ΅±:**\n```\nβ ν¬μΈνΈκ°€ λ¶€μ΅±ν•©λ‹λ‹¤.\n```\n\n2οΈβƒ£ **μλ»λ κ¶ν• μ…λ ¥:**\n```\nβ μ ν¨ν•μ§€ μ•μ€ κ¶ν•μ…λ‹λ‹¤.\n```\n\n3οΈβƒ£ **μ„ ν–‰ κ¶ν• μ—†μ:**\n```\nβ μ„ ν–‰ κ¶ν•μ„ λ¨Όμ € μ–»μΌμ…”μ•Ό ν•©λ‹λ‹¤! (LOCAL_MUSICμ΄ ν•„μ”ν•©λ‹λ‹¤)\n```\n\n---\n\n## π“ **κ¶ν• μ—…κ·Έλ μ΄λ“ κ³Όμ •**\n\n1οΈβƒ£ **λ³΄μ  ν¬μΈνΈ ν™•μΈ**\n2οΈβƒ£ **κµ¬λ§¤ν•κ³ μ ν•λ” κ¶ν• μ„ νƒ**\n3οΈβƒ£ **λ…λ Ήμ–΄ μ…λ ¥ ν›„ ν¬μΈνΈ μ°¨κ° λ° κ¶ν• μλ™ λ¶€μ—¬**\n4οΈβƒ£ **μ¦‰μ‹ κ¶ν• μ μ© λ° κΈ°λ¥ ν•΄μ **\n\n---\n\n## π”„ **κ¶ν• λ° ν¬μΈνΈ μ‹μ¤ν… μ—…λ°μ΄νΈ μ•λ‚΄**\n\nπ“ κ¶ν• μ‹μ¤ν…μ€ **μ„μ‹μ μΌλ΅ μ΄μ μ¤‘μ΄λ©°**, κΈ°λ¥κ³Ό κ°€κ²©μ΄ λ³€κ²½λ  μ μμµλ‹λ‹¤.  \nπ“ μ΄λ―Έ νλ“ν• κ¶ν•μ€ **μ¶”ν›„μ—λ„ μ μ§€λλ©°**, μƒλ΅μ΄ κΈ°λ¥μ— μ μ©λ©λ‹λ‹¤.\nπ“ μƒλ΅μ΄ κ¶ν•μ΄λ‚ ν¬μΈνΈ κΈ°λ¥μ€ μ§€μ†μ μΌλ΅ μ¶”κ°€λ  μμ •μ…λ‹λ‹¤.\n\n---\n\n> **π’΅ ν:**\n> - ν¬μΈνΈλ¥Ό ν¨μ¨μ μΌλ΅ μ‚¬μ©ν•μ—¬ ν•„μ”ν• κ¶ν•μ„ μ „λµμ μΌλ΅ ν•΄μ ν•΄λ³΄μ„Έμ”.\n> - μ νλΈλ¥Ό μμ λ΅­κ² μ¶”κ°€ν•κ³  μ‹¶λ‹¤λ©΄ `URL_UNLIMIT`!\n> - λ΅μ»¬ μμ•… μ¬μƒμ„ μ›ν•λ‹¤λ©΄ `LOCAL_MUSIC`μ„ λ¨Όμ € ν•΄μ ν• ν›„ `LOCAL_MUSIC_UP`κΉμ§€ λ„μ „!\n\n---\n\n**μ΄μ  `/κ¶ν•μ—…κΈ€`λ΅ μ›ν•λ” κΈ°λ¥μ„ μμ λ΅­κ² ν•΄μ ν•κ³  λƒ¥μ΄λ΄‡μ λ¨λ“  κΈ°λ¥μ„ ν™μ©ν•μ„Έμ”! π…πΊ**"
  }
  